{
  "node": [
    {
      "label": "Genes",
      "icon": "category-gene",
      "count": 558400
    },
    {
      "label": "Phenotypes",
      "icon": "category-phenotypic-quality",
      "count": 117141
    },
    {
      "label": "Diseases",
      "icon": "category-disease",
      "count": 26860
    },
    {
      "label": "Total Nodes",
      "icon": "node",
      "count": 860203
    }
  ],
  "association": [
    {
      "label": "Gene to Disease",
      "icon": "association-gene-to-disease",
      "count": 15032
    },
    {
      "label": "Gene to Phenotype",
      "icon": "association-gene-to-phenotype",
      "count": 882741
    },
    {
      "label": "Disease to Phenotype",
      "icon": "association-disease-to-phenotype",
      "count": 240274
    },
    {
      "label": "Total Associations",
      "icon": "association",
      "count": 10052263
    }
  ]
}
